[
  {
    "id": 1,
    "title": "Netflix",
    "amount": 12.99,
    "date": "2021-01-01",
    "type": "expense",
    "category": "Entertainment",
    "icon": "<svg xmlns='http://www.w3.org/2000/svg' viewBox='0 0 20 20' fill='currentColor' class='w-6 h-6'><path fill-rule='evenodd' d='M6 5v1H4.667a1.75 1.75 0 0 0-1.743 1.598l-.826 9.5A1.75 1.75 0 0 0 3.84 19H16.16a1.75 1.75 0 0 0 1.743-1.902l-.826-9.5A1.75 1.75 0 0 0 15.333 6H14V5a4 4 0 0 0-8 0Zm4-2.5A2.5 2.5 0 0 0 7.5 5v1h5V5A2.5 2.5 0 0 0 10 2.5ZM7.5 10a2.5 2.5 0 0 0 5 0V8.75a.75.75 0 0 1 1.5 0V10a4 4 0 0 1-8 0V8.75a.75.75 0 0 1 1.5 0V10Z' clip-rule='evenodd' /></svg>"
  },
  {
    "id": 2,
    "title": "Paycheck",
    "amount": 2000,
    "date": "2021-01-01",
    "type": "income",
    "category": "Salary",
    "icon": "<svg xmlns='http://www.w3.org/2000/svg' viewBox='0 0 20 20' fill='currentColor' class='w-6 h-6'><path fill-rule='evenodd' d='M6 5v1H4.667a1.75 1.75 0 0 0-1.743 1.598l-.826 9.5A1.75 1.75 0 0 0 3.84 19H16.16a1.75 1.75 0 0 0 1.743-1.902l-.826-9.5A1.75 1.75 0 0 0 15.333 6H14V5a4 4 0 0 0-8 0Zm4-2.5A2.5 2.5 0 0 0 7.5 5v1h5V5A2.5 2.5 0 0 0 10 2.5ZM7.5 10a2.5 2.5 0 0 0 5 0V8.75a.75.75 0 0 1 1.5 0V10a4 4 0 0 1-8 0V8.75a.75.75 0 0 1 1.5 0V10Z' clip-rule='evenodd' /></svg>"
  },
  {
    "id": 3,
    "title": "Amazon",
    "amount": 100,
    "date": "2021-01-01",
    "type": "expense",
    "category": "Shopping",
    "icon": "<svg xmlns='http://www.w3.org/2000/svg' viewBox='0 0 20 20' fill='currentColor' class='w-6 h-6'><path fill-rule='evenodd' d='M6 5v1H4.667a1.75 1.75 0 0 0-1.743 1.598l-.826 9.5A1.75 1.75 0 0 0 3.84 19H16.16a1.75 1.75 0 0 0 1.743-1.902l-.826-9.5A1.75 1.75 0 0 0 15.333 6H14V5a4 4 0 0 0-8 0Zm4-2.5A2.5 2.5 0 0 0 7.5 5v1h5V5A2.5 2.5 0 0 0 10 2.5ZM7.5 10a2.5 2.5 0 0 0 5 0V8.75a.75.75 0 0 1 1.5 0V10a4 4 0 0 1-8 0V8.75a.75.75 0 0 1 1.5 0V10Z' clip-rule='evenodd' /></svg>"
  },
  {
    "id": 4,
    "title": "Paycheck",
    "amount": 2000,
    "date": "2021-01-01",
    "type": "income",
    "category": "Salary",
    "icon": "<svg xmlns='http://www.w3.org/2000/svg' viewBox='0 0 20 20' fill='currentColor' class='w-6 h-6'><path fill-rule='evenodd' d='M6 5v1H4.667a1.75 1.75 0 0 0-1.743 1.598l-.826 9.5A1.75 1.75 0 0 0 3.84 19H16.16a1.75 1.75 0 0 0 1.743-1.902l-.826-9.5A1.75 1.75 0 0 0 15.333 6H14V5a4 4 0 0 0-8 0Zm4-2.5A2.5 2.5 0 0 0 7.5 5v1h5V5A2.5 2.5 0 0 0 10 2.5ZM7.5 10a2.5 2.5 0 0 0 5 0V8.75a.75.75 0 0 1 1.5 0V10a4 4 0 0 1-8 0V8.75a.75.75 0 0 1 1.5 0V10Z' clip-rule='evenodd' /></svg>"
  },
  {
    "id": 5,
    "title": "Amazon",
    "amount": 100,
    "date": "2021-01-01",
    "type": "expense",
    "category": "Shopping",
    "icon": "<svg xmlns='http://www.w3.org/2000/svg' viewBox='0 0 20 20' fill='currentColor' class='w-6 h-6'><path fill-rule='evenodd' d='M6 5v1H4.667a1.75 1.75 0 0 0-1.743 1.598l-.826 9.5A1.75 1.75 0 0 0 3.84 19H16.16a1.75 1.75 0 0 0 1.743-1.902l-.826-9.5A1.75 1.75 0 0 0 15.333 6H14V5a4 4 0 0 0-8 0Zm4-2.5A2.5 2.5 0 0 0 7.5 5v1h5V5A2.5 2.5 0 0 0 10 2.5ZM7.5 10a2.5 2.5 0 0 0 5 0V8.75a.75.75 0 0 1 1.5 0V10a4 4 0 0 1-8 0V8.75a.75.75 0 0 1 1.5 0V10Z' clip-rule='evenodd' /></svg>"
  },
  {
    "id": 6,
    "title": "Paycheck",
    "amount": 2000,
    "date": "2021-01-01",
    "type": "income",
    "category": "Salary",
    "icon": "<svg xmlns='http://www.w3.org/2000/svg' viewBox='0 0 20 20' fill='currentColor' class='w-6 h-6'><path fill-rule='evenodd' d='M6 5v1H4.667a1.75 1.75 0 0 0-1.743 1.598l-.826 9.5A1.75 1.75 0 0 0 3.84 19H16.16a1.75 1.75 0 0 0 1.743-1.902l-.826-9.5A1.75 1.75 0 0 0 15.333 6H14V5a4 4 0 0 0-8 0Zm4-2.5A2.5 2.5 0 0 0 7.5 5v1h5V5A2.5 2.5 0 0 0 10 2.5ZM7.5 10a2.5 2.5 0 0 0 5 0V8.75a.75.75 0 0 1 1.5 0V10a4 4 0 0 1-8 0V8.75a.75.75 0 0 1 1.5 0V10Z' clip-rule='evenodd' /></svg>"
  },
  {
    "id": 7,
    "title": "Amazon",
    "amount": 100,
    "date": "2021-01-01",
    "type": "expense",
    "category": "Shopping",
    "icon": "<svg xmlns='http://www.w3.org/2000/svg' viewBox='0 0 20 20' fill='currentColor' class='w-6 h-6'><path fill-rule='evenodd' d='M6 5v1H4.667a1.75 1.75 0 0 0-1.743 1.598l-.826 9.5A1.75 1.75 0 0 0 3.84 19H16.16a1.75 1.75 0 0 0 1.743-1.902l-.826-9.5A1.75 1.75 0 0 0 15.333 6H14V5a4 4 0 0 0-8 0Zm4-2.5A2.5 2.5 0 0 0 7.5 5v1h5V5A2.5 2.5 0 0 0 10 2.5ZM7.5 10a2.5 2.5 0 0 0 5 0V8.75a.75.75 0 0 1 1.5 0V10a4 4 0 0 1-8 0V8.75a.75.75 0 0 1 1.5 0V10Z' clip-rule='evenodd' /></svg>"
  },
  {
    "id": 8,
    "title": "Paycheck",
    "amount": 2000,
    "date": "2021-01-01",
    "type": "income",
    "category": "Salary",
    "icon": "<svg xmlns='http://www.w3.org/2000/svg' viewBox='0 0 20 20' fill='currentColor' class='w-6 h-6'><path fill-rule='evenodd' d='M6 5v1H4.667a1.75 1.75 0 0 0-1.743 1.598l-.826 9.5A1.75 1.75 0 0 0 3.84 19H16.16a1.75 1.75 0 0 0 1.743-1.902l-.826-9.5A1.75 1.75 0 0 0 15.333 6H14V5a4 4 0 0 0-8 0Zm4-2.5A2.5 2.5 0 0 0 7.5 5v1h5V5A2.5 2.5 0 0 0 10 2.5ZM7.5 10a2.5 2.5 0 0 0 5 0V8.75a.75.75 0 0 1 1.5 0V10a4 4 0 0 1-8 0V8.75a.75.75 0 0 1 1.5 0V10Z' clip-rule='evenodd' /></svg>"
  },
  {
    "id": 9,
    "title": "Amazon",
    "amount": 100,
    "date": "2021-01-01",
    "type": "expense",
    "category": "Shopping",
    "icon": "<svg xmlns='http://www.w3.org/2000/svg' viewBox='0 0 20 20' fill='currentColor' class='w-6 h-6'><path fill-rule='evenodd' d='M6 5v1H4.667a1.75 1.75 0 0 0-1.743 1.598l-.826 9.5A1.75 1.75 0 0 0 3.84 19H16.16a1.75 1.75 0 0 0 1.743-1.902l-.826-9.5A1.75 1.75 0 0 0 15.333 6H14V5a4 4 0 0 0-8 0Zm4-2.5A2.5 2.5 0 0 0 7.5 5v1h5V5A2.5 2.5 0 0 0 10 2.5ZM7.5 10a2.5 2.5 0 0 0 5 0V8.75a.75.75 0 0 1 1.5 0V10a4 4 0 0 1-8 0V8.75a.75.75 0 0 1 1.5 0V10Z' clip-rule='evenodd' /></svg>"
  },
  {
    "id": 10,
    "title": "Paycheck",
    "amount": 2000,
    "date": "2021-01-01",
    "type": "income",
    "category": "Salary",
    "icon": "<svg xmlns='http://www.w3.org/2000/svg' viewBox='0 0 20 20' fill='currentColor' class='w-6 h-6'><path fill-rule='evenodd' d='M6 5v1H4.667a1.75 1.75 0 0 0-1.743 1.598l-.826 9.5A1.75 1.75 0 0 0 3.84 19H16.16a1.75 1.75 0 0 0 1.743-1.902l-.826-9.5A1.75 1.75 0 0 0 15.333 6H14V5a4 4 0 0 0-8 0Zm4-2.5A2.5 2.5 0 0 0 7.5 5v1h5V5A2.5 2.5 0 0 0 10 2.5ZM7.5 10a2.5 2.5 0 0 0 5 0V8.75a.75.75 0 0 1 1.5 0V10a4 4 0 0 1-8 0V8.75a.75.75 0 0 1 1.5 0V10Z' clip-rule='evenodd' /></svg>"
  },
  {
    "id": 11,
    "title": "Amazon",
    "amount": 100,
    "date": "2021-01-01",
    "type": "expense",
    "category": "Shopping",
    "icon": "<svg xmlns='http://www.w3.org/2000/svg' viewBox='0 0 20 20' fill='currentColor' class='w-6 h-6'><path fill-rule='evenodd' d='M6 5v1H4.667a1.75 1.75 0 0 0-1.743 1.598l-.826 9.5A1.75 1.75 0 0 0 3.84 19H16.16a1.75 1.75 0 0 0 1.743-1.902l-.826-9.5A1.75 1.75 0 0 0 15.333 6H14V5a4 4 0 0 0-8 0Zm4-2.5A2.5 2.5 0 0 0 7.5 5v1h5V5A2.5 2.5 0 0 0 10 2.5ZM7.5 10a2.5 2.5 0 0 0 5 0V8.75a.75.75 0 0 1 1.5 0V10a4 4 0 0 1-8 0V8.75a.75.75 0 0 1 1.5 0V10Z' clip-rule='evenodd' /></svg>"
  },
  {
    "id": 12,
    "title": "Paycheck",
    "amount": 2000,
    "date": "2021-01-01",
    "type": "income",
    "category": "Salary",
    "icon": "<svg xmlns='http://www.w3.org/2000/svg' viewBox='0 0 20 20' fill='currentColor' class='w-6 h-6'><path fill-rule='evenodd' d='M6 5v1H4.667a1.75 1.75 0 0 0-1.743 1.598l-.826 9.5A1.75 1.75 0 0 0 3.84 19H16.16a1.75 1.75 0 0 0 1.743-1.902l-.826-9.5A1.75 1.75 0 0 0 15.333 6H14V5a4 4 0 0 0-8 0Zm4-2.5A2.5 2.5 0 0 0 7.5 5v1h5V5A2.5 2.5 0 0 0 10 2.5ZM7.5 10a2.5 2.5 0 0 0 5 0V8.75a.75.75 0 0 1 1.5 0V10a4 4 0 0 1-8 0V8.75a.75.75 0 0 1 1.5 0V10Z' clip-rule='evenodd' /></svg>"
  },
  {
    "id": 13,
    "title": "Amazon",
    "amount": 100,
    "date": "2021-01-01",
    "type": "expense",
    "category": "Shopping",
    "icon": "<svg xmlns='http://www.w3.org/2000/svg' viewBox='0 0 20 20' fill='currentColor' class='w-6 h-6'><path fill-rule='evenodd' d='M6 5v1H4.667a1.75 1.75 0 0 0-1.743 1.598l-.826 9.5A1.75 1.75 0 0 0 3.84 19H16.16a1.75 1.75 0 0 0 1.743-1.902l-.826-9.5A1.75 1.75 0 0 0 15.333 6H14V5a4 4 0 0 0-8 0Zm4-2.5A2.5 2.5 0 0 0 7.5 5v1h5V5A2.5 2.5 0 0 0 10 2.5ZM7.5 10a2.5 2.5 0 0 0 5 0V8.75a.75.75 0 0 1 1.5 0V10a4 4 0 0 1-8 0V8.75a.75.75 0 0 1 1.5 0V10Z' clip-rule='evenodd' /></svg>"
  },
  {
    "id": 14,
    "title": "Paycheck",
    "amount": 2000,
    "date": "2021-01-01",
    "type": "income",
    "category": "Salary",
    "icon": "<svg xmlns='http://www.w3.org/2000/svg' viewBox='0 0 20 20' fill='currentColor' class='w-6 h-6'><path fill-rule='evenodd' d='M6 5v1H4.667a1.75 1.75 0 0 0-1.743 1.598l-.826 9.5A1.75 1.75 0 0 0 3.84 19H16.16a1.75 1.75 0 0 0 1.743-1.902l-.826-9.5A1.75 1.75 0 0 0 15.333 6H14V5a4 4 0 0 0-8 0Zm4-2.5A2.5 2.5 0 0 0 7.5 5v1h5V5A2.5 2.5 0 0 0 10 2.5ZM7.5 10a2.5 2.5 0 0 0 5 0V8.75a.75.75 0 0 1 1.5 0V10a4 4 0 0 1-8 0V8.75a.75.75 0 0 1 1.5 0V10Z' clip-rule='evenodd' /></svg>"
  },
  {
    "id": 15,
    "title": "Amazon",
    "amount": 100,
    "date": "2021-01-01",
    "type": "expense",
    "category": "Shopping",
    "icon": "<svg xmlns='http://www.w3.org/2000/svg' viewBox='0 0 20 20' fill='currentColor' class='w-6 h-6'><path fill-rule='evenodd' d='M6 5v1H4.667a1.75 1.75 0 0 0-1.743 1.598l-.826 9.5A1.75 1.75 0 0 0 3.84 19H16.16a1.75 1.75 0 0 0 1.743-1.902l-.826-9.5A1.75 1.75 0 0 0 15.333 6H14V5a4 4 0 0 0-8 0Zm4-2.5A2.5 2.5 0 0 0 7.5 5v1h5V5A2.5 2.5 0 0 0 10 2.5ZM7.5 10a2.5 2.5 0 0 0 5 0V8.75a.75.75 0 0 1 1.5 0V10a4 4 0 0 1-8 0V8.75a.75.75 0 0 1 1.5 0V10Z' clip-rule='evenodd' /></svg>"
  }
]
